Metadata-Version: 2.1
Name: aug
Version: 0.2.4
Summary: Augmentation library based on OpenCV.
Home-page: https://github.com/cta-ai/aug
Author: Tomasz Gilewicz
Author-email: tomasz.gilewicz1@gmail.com
License: Apache License 2.0
Keywords: data augmentation artificial synthesis machine learning
Platform: UNKNOWN
Classifier: Programming Language :: Python :: 3
Classifier: Operating System :: OS Independent
Requires-Dist: imageio (>=2.5.0)
Requires-Dist: matplotlib (>=3.1.0)
Requires-Dist: numpy (>=1.16.4)
Requires-Dist: opencv-python (>=4.1.0.25)
Requires-Dist: Pillow (>=6.0.0)
Requires-Dist: requests (>=2.22.0)
Requires-Dist: scipy (>=1.3.0)
